swaps_gateway/__init__.py
swaps_gateway/erc20_abi.txt
swaps_gateway/router_abi.txt
swaps_gateway/uniswap_ecosystem.py
swaps_gateway-0.1.1.dist-info/METADATA
swaps_gateway-0.1.1.dist-info/WHEEL
swaps_gateway-0.1.1.dist-info/top_level.txt
swaps_gateway-0.1.1.dist-info/RECORD
